dataguard/__init__.py
dataguard/db_connect.py
dataguard/anomaly_detection/Anomaly_detection_using_std.py
dataguard/anomaly_detection/__init__.py
dataguard/data_profiling/__init__.py
dataguard/data_profiling/profiling.py
dataguard/dq_rules/__init__.py
dataguard/dq_rules/rules_master.py
dataguard/dq_rules/sigmadq_core_functions.py
dataguard/dq_rules/sigmadq_helper_functions.py
dataguard_2-0.1.0.dist-info/LICENCE.md
dataguard_2-0.1.0.dist-info/METADATA
dataguard_2-0.1.0.dist-info/WHEEL
dataguard_2-0.1.0.dist-info/top_level.txt
dataguard_2-0.1.0.dist-info/RECORD
