Metadata-Version: 2.1
Name: dataguard-2
Version: 0.1.0
Summary: Data quality tools
Home-page: UNKNOWN
Author: Anirudha Bidave
Author-email: anirudha.b@sigmoidanalytics.com
License: UNKNOWN
Platform: UNKNOWN
Classifier: Programming Language :: Python :: 3
Classifier: License :: OSI Approved :: MIT License
Classifier: Operating System :: OS Independent
License-File: LICENCE.md
Requires-Dist: adal==1.2.7
Requires-Dist: alembic==1.13.2
Requires-Dist: annotated-types==0.7.0
Requires-Dist: asn1crypto==1.5.1
Requires-Dist: attrs==23.2.0
Requires-Dist: cachetools==5.4.0
Requires-Dist: certifi==2024.7.4
Requires-Dist: cffi==1.16.0
Requires-Dist: charset-normalizer==3.3.2
Requires-Dist: contourpy==1.2.1
Requires-Dist: cryptography==42.0.8
Requires-Dist: cycler==0.12.1
Requires-Dist: dacite==1.8.1
Requires-Dist: databricks-sql-connector==2.9.6
Requires-Dist: et-xmlfile==1.1.0
Requires-Dist: filelock==3.15.4
Requires-Dist: fonttools==4.53.1
Requires-Dist: future==1.0.0
Requires-Dist: google-api-core==2.19.1
Requires-Dist: google-auth==2.32.0
Requires-Dist: google-cloud-bigquery==3.25.0
Requires-Dist: google-cloud-core==2.4.1
Requires-Dist: google-crc32c==1.5.0
Requires-Dist: google-resumable-media==2.7.1
Requires-Dist: googleapis-common-protos==1.63.2
Requires-Dist: grpcio==1.64.1
Requires-Dist: grpcio-status==1.64.1
Requires-Dist: htmlmin==0.1.12
Requires-Dist: idna==3.7
Requires-Dist: ImageHash==4.3.1
Requires-Dist: importlib-metadata==8.0.0
Requires-Dist: importlib-resources==6.4.0
Requires-Dist: Jinja2==3.1.4
Requires-Dist: joblib==1.4.2
Requires-Dist: kiwisolver==1.4.5
Requires-Dist: llvmlite==0.43.0
Requires-Dist: lz4==4.3.3
Requires-Dist: Mako==1.3.5
Requires-Dist: MarkupSafe==2.1.5
Requires-Dist: matplotlib==3.9.1
Requires-Dist: multimethod==1.12
Requires-Dist: networkx==3.2.1
Requires-Dist: numba==0.60.0
Requires-Dist: numpy==1.26.4
Requires-Dist: oauthlib==3.2.2
Requires-Dist: openpyxl==3.1.5
Requires-Dist: packaging==24.1
Requires-Dist: pandas==2.2.2
Requires-Dist: patsy==0.5.6
Requires-Dist: phik==0.12.4
Requires-Dist: pillow==10.4.0
Requires-Dist: platformdirs==4.2.2
Requires-Dist: proto-plus==1.24.0
Requires-Dist: protobuf==5.27.2
Requires-Dist: psycopg2-binary==2.9.9
Requires-Dist: py4j==0.10.9.7
Requires-Dist: pyarrow==16.1.0
Requires-Dist: pyasn1==0.6.0
Requires-Dist: pyasn1-modules==0.4.0
Requires-Dist: pycparser==2.22
Requires-Dist: pydantic==2.8.2
Requires-Dist: pydantic-core==2.20.1
Requires-Dist: PyHive==0.7.0
Requires-Dist: PyJWT==2.8.0
Requires-Dist: pymsteams==0.2.3
Requires-Dist: PyMySQL==1.1.1
Requires-Dist: pyodbc==5.1.0
Requires-Dist: pyOpenSSL==24.1.0
Requires-Dist: pyparsing==3.1.2
Requires-Dist: pyspark==3.5.1
Requires-Dist: python-dateutil==2.9.0.post0
Requires-Dist: pytz==2024.1
Requires-Dist: PyWavelets==1.6.0
Requires-Dist: PyYAML==6.0.1
Requires-Dist: requests==2.32.3
Requires-Dist: rsa==4.9
Requires-Dist: scipy==1.13.1
Requires-Dist: seaborn==0.13.2
Requires-Dist: six==1.16.0
Requires-Dist: snowflake-connector-python==3.11.0
Requires-Dist: snowflake-sqlalchemy==1.6.1
Requires-Dist: sortedcontainers==2.4.0
Requires-Dist: SQLAlchemy==1.4.52
Requires-Dist: sqlalchemy-bigquery==1.11.0
Requires-Dist: sqlalchemy-databricks==0.2.0
Requires-Dist: sqlalchemy-redshift==0.8.14
Requires-Dist: statsmodels==0.14.2
Requires-Dist: thrift==0.16.0
Requires-Dist: tomlkit==0.13.0
Requires-Dist: tqdm==4.66.4
Requires-Dist: typeguard==4.3.0
Requires-Dist: typing-extensions==4.12.2
Requires-Dist: tzdata==2024.1
Requires-Dist: urllib3==1.26.19
Requires-Dist: visions==0.7.6
Requires-Dist: wordcloud==1.9.3
Requires-Dist: ydata-profiling==4.9.0
Requires-Dist: zipp==3.19.2
